cellpath/__init__.py
cellpath/__version__.py
cellpath/benchmark.py
cellpath/cellpath.py
cellpath/clustering.py
cellpath/de_analy.py
cellpath/leiden.py
cellpath/nn.py
cellpath/nn_old.py
cellpath/path.py
cellpath/princurve.py
cellpath/visual.py
cellpath-1.0.dist-info/LICENSE
cellpath-1.0.dist-info/METADATA
cellpath-1.0.dist-info/WHEEL
cellpath-1.0.dist-info/top_level.txt
cellpath-1.0.dist-info/RECORD
