Metadata-Version: 2.1
Name: cellpath
Version: 1.0
Summary: CellPath, multiple trajectories inference in single cell RNA-Seq data from RNA velocity
Home-page: https://github.com/PeterZZQ/CellPath
Author: Ziqi Zhang
Author-email: zhangziqibuaa@gmail.edu
License: GNU General Public License v3 (GPLv3)
Classifier: License :: OSI Approved :: GNU General Public License v3 (GPLv3)
Classifier: Programming Language :: Python
Classifier: Programming Language :: Python :: 3
Classifier: Programming Language :: Python :: 3.6
Classifier: Programming Language :: Python :: Implementation :: CPython
Classifier: Programming Language :: Python :: Implementation :: PyPy
Classifier: Topic :: Scientific/Engineering :: Bio-Informatics
Classifier: Operating System :: POSIX :: Linux
Classifier: Operating System :: MacOS :: MacOS X
Requires-Python: >=3.6.0
License-File: LICENSE
Requires-Dist: numpy (>=1.18.2)
Requires-Dist: networkx (>=2.5)
Requires-Dist: scipy (>=1.4.1)
Requires-Dist: pandas (>=1.1.5)
Requires-Dist: scikit-learn (>=0.22.1)
Requires-Dist: anndata (>=0.7.6)
Requires-Dist: scvelo (>=0.2.3)
Requires-Dist: statsmodels (>=0.12.1)
Requires-Dist: seaborn (>=0.10.0)
Requires-Dist: matplotlib (>=3.2.1)
Requires-Dist: leidenalg (>=0.8.2)
Provides-Extra: principal_curve
Requires-Dist: rpy2 (>=3.3.0) ; extra == 'principal_curve'
